{
  "openapi": "3.0.1",
  "info": {
    "title": "Api",
    "description": "Collection Api relative au test technique de DEVOLUTION",
    "version": "V1"
  },
  "paths": {
    "/v1/auth/login": {
      "post": {
        "tags": [
          "auth"
        ],
        "requestBody": {
          "content": {
            "application/json": {
              "schema": {
                "$ref": "#/components/schemas/AuthDTO"
              }
            },
            "text/json": {
              "schema": {
                "$ref": "#/components/schemas/AuthDTO"
              }
            },
            "application/*+json": {
              "schema": {
                "$ref": "#/components/schemas/AuthDTO"
              }
            }
          }
        },
        "responses": {
          "200": {
            "description": "Success"
          }
        }
      }
    },
    "/v1/categories/all": {
      "post": {
        "tags": [
          "categories"
        ],
        "requestBody": {
          "content": {
            "application/json": {
              "schema": {
                "$ref": "#/components/schemas/CategoryVehicleFilterSearchEntityDto"
              }
            },
            "text/json": {
              "schema": {
                "$ref": "#/components/schemas/CategoryVehicleFilterSearchEntityDto"
              }
            },
            "application/*+json": {
              "schema": {
                "$ref": "#/components/schemas/CategoryVehicleFilterSearchEntityDto"
              }
            }
          }
        },
        "responses": {
          "200": {
            "description": "Success"
          }
        }
      }
    },
    "/v1/categories/{id}": {
      "get": {
        "tags": [
          "categories"
        ],
        "parameters": [
          {
            "name": "id",
            "in": "path",
            "required": true,
            "schema": {
              "type": "string"
            }
          }
        ],
        "responses": {
          "200": {
            "description": "Success"
          }
        }
      }
    },
    "/v1/categories": {
      "post": {
        "tags": [
          "categories"
        ],
        "requestBody": {
          "content": {
            "application/json": {
              "schema": {
                "$ref": "#/components/schemas/CategoryVehicleDTO"
              }
            },
            "text/json": {
              "schema": {
                "$ref": "#/components/schemas/CategoryVehicleDTO"
              }
            },
            "application/*+json": {
              "schema": {
                "$ref": "#/components/schemas/CategoryVehicleDTO"
              }
            }
          }
        },
        "responses": {
          "200": {
            "description": "Success"
          }
        }
      }
    },
    "/v1/products/all": {
      "post": {
        "tags": [
          "products"
        ],
        "requestBody": {
          "content": {
            "application/json": {
              "schema": {
                "$ref": "#/components/schemas/AssurProductFilterSearchEntityDto"
              }
            },
            "text/json": {
              "schema": {
                "$ref": "#/components/schemas/AssurProductFilterSearchEntityDto"
              }
            },
            "application/*+json": {
              "schema": {
                "$ref": "#/components/schemas/AssurProductFilterSearchEntityDto"
              }
            }
          }
        },
        "responses": {
          "200": {
            "description": "Success"
          }
        }
      }
    },
    "/v1/products/{id}": {
      "get": {
        "tags": [
          "products"
        ],
        "parameters": [
          {
            "name": "id",
            "in": "path",
            "required": true,
            "schema": {
              "type": "string"
            }
          }
        ],
        "responses": {
          "200": {
            "description": "Success"
          }
        }
      }
    },
    "/v1/products": {
      "post": {
        "tags": [
          "products"
        ],
        "requestBody": {
          "content": {
            "application/json": {
              "schema": {
                "$ref": "#/components/schemas/AssurProductDTO"
              }
            },
            "text/json": {
              "schema": {
                "$ref": "#/components/schemas/AssurProductDTO"
              }
            },
            "application/*+json": {
              "schema": {
                "$ref": "#/components/schemas/AssurProductDTO"
              }
            }
          }
        },
        "responses": {
          "200": {
            "description": "Success"
          }
        }
      }
    },
    "/v1/simulations/all": {
      "post": {
        "tags": [
          "simulations"
        ],
        "requestBody": {
          "content": {
            "application/json": {
              "schema": {
                "$ref": "#/components/schemas/SimulationFilterSearchEntityDto"
              }
            },
            "text/json": {
              "schema": {
                "$ref": "#/components/schemas/SimulationFilterSearchEntityDto"
              }
            },
            "application/*+json": {
              "schema": {
                "$ref": "#/components/schemas/SimulationFilterSearchEntityDto"
              }
            }
          }
        },
        "responses": {
          "200": {
            "description": "Success"
          }
        }
      }
    },
    "/v1/simulations/{id}": {
      "get": {
        "tags": [
          "simulations"
        ],
        "parameters": [
          {
            "name": "id",
            "in": "path",
            "required": true,
            "schema": {
              "type": "string"
            }
          }
        ],
        "responses": {
          "200": {
            "description": "Success"
          }
        }
      }
    },
    "/v1/simulations": {
      "post": {
        "tags": [
          "simulations"
        ],
        "requestBody": {
          "content": {
            "application/json": {
              "schema": {
                "$ref": "#/components/schemas/SimulationDTO"
              }
            },
            "text/json": {
              "schema": {
                "$ref": "#/components/schemas/SimulationDTO"
              }
            },
            "application/*+json": {
              "schema": {
                "$ref": "#/components/schemas/SimulationDTO"
              }
            }
          }
        },
        "responses": {
          "200": {
            "description": "Success"
          }
        }
      }
    },
    "/v1/subscriptions/all": {
      "post": {
        "tags": [
          "subscriptions"
        ],
        "requestBody": {
          "content": {
            "application/json": {
              "schema": {
                "$ref": "#/components/schemas/SubscriptionFilterSearchEntityDto"
              }
            },
            "text/json": {
              "schema": {
                "$ref": "#/components/schemas/SubscriptionFilterSearchEntityDto"
              }
            },
            "application/*+json": {
              "schema": {
                "$ref": "#/components/schemas/SubscriptionFilterSearchEntityDto"
              }
            }
          }
        },
        "responses": {
          "200": {
            "description": "Success"
          }
        }
      }
    },
    "/v1/subscriptions/{id}": {
      "get": {
        "tags": [
          "subscriptions"
        ],
        "parameters": [
          {
            "name": "id",
            "in": "path",
            "required": true,
            "schema": {
              "type": "string"
            }
          }
        ],
        "responses": {
          "200": {
            "description": "Success"
          }
        }
      }
    },
    "/v1/subscriptions/status/{id}": {
      "get": {
        "tags": [
          "subscriptions"
        ],
        "parameters": [
          {
            "name": "id",
            "in": "path",
            "required": true,
            "schema": {
              "type": "string"
            }
          }
        ],
        "responses": {
          "200": {
            "description": "Success"
          }
        }
      }
    },
    "/v1/subscriptions/{id}/attestation": {
      "get": {
        "tags": [
          "subscriptions"
        ],
        "parameters": [
          {
            "name": "id",
            "in": "path",
            "required": true,
            "schema": {
              "type": "string"
            }
          }
        ],
        "responses": {
          "200": {
            "description": "Success"
          }
        }
      }
    },
    "/v1/subscriptions": {
      "post": {
        "tags": [
          "subscriptions"
        ],
        "requestBody": {
          "content": {
            "application/json": {
              "schema": {
                "$ref": "#/components/schemas/SubscriptionDTO"
              }
            },
            "text/json": {
              "schema": {
                "$ref": "#/components/schemas/SubscriptionDTO"
              }
            },
            "application/*+json": {
              "schema": {
                "$ref": "#/components/schemas/SubscriptionDTO"
              }
            }
          }
        },
        "responses": {
          "200": {
            "description": "Success"
          }
        }
      }
    },
    "/v1/suscribers/all": {
      "post": {
        "tags": [
          "suscribers"
        ],
        "requestBody": {
          "content": {
            "application/json": {
              "schema": {
                "$ref": "#/components/schemas/SuscriberFilterSearchEntityDto"
              }
            },
            "text/json": {
              "schema": {
                "$ref": "#/components/schemas/SuscriberFilterSearchEntityDto"
              }
            },
            "application/*+json": {
              "schema": {
                "$ref": "#/components/schemas/SuscriberFilterSearchEntityDto"
              }
            }
          }
        },
        "responses": {
          "200": {
            "description": "Success"
          }
        }
      }
    },
    "/v1/suscribers/{id}": {
      "get": {
        "tags": [
          "suscribers"
        ],
        "parameters": [
          {
            "name": "id",
            "in": "path",
            "required": true,
            "schema": {
              "type": "string"
            }
          }
        ],
        "responses": {
          "200": {
            "description": "Success"
          }
        }
      }
    },
    "/v1/vehicles/all": {
      "post": {
        "tags": [
          "vehicles"
        ],
        "requestBody": {
          "content": {
            "application/json": {
              "schema": {
                "$ref": "#/components/schemas/VehicleFilterSearchEntityDto"
              }
            },
            "text/json": {
              "schema": {
                "$ref": "#/components/schemas/VehicleFilterSearchEntityDto"
              }
            },
            "application/*+json": {
              "schema": {
                "$ref": "#/components/schemas/VehicleFilterSearchEntityDto"
              }
            }
          }
        },
        "responses": {
          "200": {
            "description": "Success"
          }
        }
      }
    },
    "/v1/vehicles/{id}": {
      "get": {
        "tags": [
          "vehicles"
        ],
        "parameters": [
          {
            "name": "id",
            "in": "path",
            "required": true,
            "schema": {
              "type": "string"
            }
          }
        ],
        "responses": {
          "200": {
            "description": "Success"
          }
        }
      }
    }
  },
  "components": {
    "schemas": {
      "AssurProductDTO": {
        "type": "object",
        "properties": {
          "name": {
            "type": "string",
            "nullable": true
          },
          "garanties": {
            "type": "array",
            "items": {
              "type": "string"
            },
            "nullable": true
          },
          "categories": {
            "type": "array",
            "items": {
              "type": "string"
            },
            "nullable": true
          },
          "createdBy": {
            "type": "string",
            "nullable": true
          },
          "updatedBy": {
            "type": "string",
            "nullable": true
          }
        },
        "additionalProperties": false
      },
      "AssurProductFilter": {
        "type": "object",
        "properties": {
          "name": {
            "type": "string",
            "nullable": true
          }
        },
        "additionalProperties": false
      },
      "AssurProductFilterSearchEntityDto": {
        "type": "object",
        "properties": {
          "pageIndex": {
            "type": "integer",
            "format": "int32"
          },
          "pageSize": {
            "type": "integer",
            "format": "int32"
          },
          "filter": {
            "$ref": "#/components/schemas/AssurProductFilter"
          }
        },
        "additionalProperties": false
      },
      "AuthDTO": {
        "type": "object",
        "properties": {
          "username": {
            "type": "string",
            "nullable": true
          },
          "password": {
            "type": "string",
            "nullable": true
          }
        },
        "additionalProperties": false
      },
      "CategoryVehicleDTO": {
        "type": "object",
        "properties": {
          "code": {
            "type": "string",
            "nullable": true
          },
          "libelle": {
            "type": "string",
            "nullable": true
          },
          "description": {
            "type": "string",
            "nullable": true
          },
          "createdBy": {
            "type": "string",
            "nullable": true
          },
          "updatedBy": {
            "type": "string",
            "nullable": true
          }
        },
        "additionalProperties": false
      },
      "CategoryVehicleFilter": {
        "type": "object",
        "properties": {
          "code": {
            "type": "string",
            "nullable": true
          },
          "libelle": {
            "type": "string",
            "nullable": true
          }
        },
        "additionalProperties": false
      },
      "CategoryVehicleFilterSearchEntityDto": {
        "type": "object",
        "properties": {
          "pageIndex": {
            "type": "integer",
            "format": "int32"
          },
          "pageSize": {
            "type": "integer",
            "format": "int32"
          },
          "filter": {
            "$ref": "#/components/schemas/CategoryVehicleFilter"
          }
        },
        "additionalProperties": false
      },
      "SimulationDTO": {
        "type": "object",
        "properties": {
          "idAssurProduct": {
            "type": "string",
            "nullable": true
          },
          "vehicle": {
            "$ref": "#/components/schemas/VehicleDTO"
          },
          "createdBy": {
            "type": "string",
            "nullable": true
          },
          "updatedBy": {
            "type": "string",
            "nullable": true
          }
        },
        "additionalProperties": false
      },
      "SimulationFilter": {
        "type": "object",
        "properties": {
          "quoteReference": {
            "type": "string",
            "nullable": true
          }
        },
        "additionalProperties": false
      },
      "SimulationFilterSearchEntityDto": {
        "type": "object",
        "properties": {
          "pageIndex": {
            "type": "integer",
            "format": "int32"
          },
          "pageSize": {
            "type": "integer",
            "format": "int32"
          },
          "filter": {
            "$ref": "#/components/schemas/SimulationFilter"
          }
        },
        "additionalProperties": false
      },
      "SubscriptionDTO": {
        "type": "object",
        "properties": {
          "idAssurProduct": {
            "type": "string",
            "nullable": true
          },
          "vehicle": {
            "$ref": "#/components/schemas/VehicleDTO"
          },
          "suscriber": {
            "$ref": "#/components/schemas/SuscriberDTO"
          },
          "createdBy": {
            "type": "string",
            "nullable": true
          },
          "updatedBy": {
            "type": "string",
            "nullable": true
          }
        },
        "additionalProperties": false
      },
      "SubscriptionFilter": {
        "type": "object",
        "properties": {
          "quoteReference": {
            "type": "string",
            "nullable": true
          }
        },
        "additionalProperties": false
      },
      "SubscriptionFilterSearchEntityDto": {
        "type": "object",
        "properties": {
          "pageIndex": {
            "type": "integer",
            "format": "int32"
          },
          "pageSize": {
            "type": "integer",
            "format": "int32"
          },
          "filter": {
            "$ref": "#/components/schemas/SubscriptionFilter"
          }
        },
        "additionalProperties": false
      },
      "SuscriberDTO": {
        "type": "object",
        "properties": {
          "address": {
            "type": "string",
            "nullable": true
          },
          "cni": {
            "type": "string",
            "nullable": true
          },
          "nom": {
            "type": "string",
            "nullable": true
          },
          "prenom": {
            "type": "string",
            "nullable": true
          },
          "ville": {
            "type": "string",
            "nullable": true
          },
          "telephone": {
            "type": "string",
            "nullable": true
          },
          "createdBy": {
            "type": "string",
            "nullable": true
          },
          "updatedBy": {
            "type": "string",
            "nullable": true
          }
        },
        "additionalProperties": false
      },
      "SuscriberFilter": {
        "type": "object",
        "properties": {
          "telephone": {
            "type": "string",
            "nullable": true
          },
          "cni": {
            "type": "string",
            "nullable": true
          }
        },
        "additionalProperties": false
      },
      "SuscriberFilterSearchEntityDto": {
        "type": "object",
        "properties": {
          "pageIndex": {
            "type": "integer",
            "format": "int32"
          },
          "pageSize": {
            "type": "integer",
            "format": "int32"
          },
          "filter": {
            "$ref": "#/components/schemas/SuscriberFilter"
          }
        },
        "additionalProperties": false
      },
      "VehicleDTO": {
        "type": "object",
        "properties": {
          "couleur": {
            "type": "string",
            "nullable": true
          },
          "idCategoryVehicle": {
            "type": "string",
            "nullable": true
          },
          "dateFirstUse": {
            "type": "string",
            "format": "date-time"
          },
          "siegeNumber": {
            "type": "integer",
            "format": "int32"
          },
          "porteNumber": {
            "type": "integer",
            "format": "int32"
          },
          "immatriculation": {
            "type": "string",
            "nullable": true
          },
          "valueNeuve": {
            "type": "number",
            "format": "double"
          },
          "valueVenale": {
            "type": "number",
            "format": "double"
          },
          "fiscalPower": {
            "type": "integer",
            "format": "int32"
          },
          "createdBy": {
            "type": "string",
            "nullable": true
          },
          "updatedBy": {
            "type": "string",
            "nullable": true
          }
        },
        "additionalProperties": false
      },
      "VehicleFilter": {
        "type": "object",
        "properties": {
          "immatriculationNumber": {
            "type": "string",
            "nullable": true
          }
        },
        "additionalProperties": false
      },
      "VehicleFilterSearchEntityDto": {
        "type": "object",
        "properties": {
          "pageIndex": {
            "type": "integer",
            "format": "int32"
          },
          "pageSize": {
            "type": "integer",
            "format": "int32"
          },
          "filter": {
            "$ref": "#/components/schemas/VehicleFilter"
          }
        },
        "additionalProperties": false
      }
    }
  }
}